{
    "data_class": "carrefour_all_cls.pkl",
    "trainer_config": {
        "tune": {
            "metrics": {
                "loss": "train_loss",
                "recall": "bert_recall@1"
            },
            "resources_per_trial": {
                "cpu": 12,
                "gpu": 1
            },
            "tune_config": {
                "metric": "recall",
                "mode": "max",
                "num_samples": 4
            }
        },
        "early_stopping": {
            "monitor": "bert_recall@1",
            "patience": 10,
            "verbose": false,
            "mode": "max"
        },
        "limit_train_batches": 0.5,
        "max_epochs": 5,
        "sample_size": 128,
        "sample_method": "random",
        "seed": 12345,
        "num_workers": 12
    },
    "model_params": {
        "batch_size": [
            16,
            32
        ],
        "mask_prob": [
            0.15
        ],
        "hidden_size": [
            64,
            128,
            256
        ],
        "n_layers": [
            2,
            3
        ],
        "dropout": [
            0,
            0.1,
            0.2
        ],
        "max_len": [
            64,
            128,
            256,
            512
        ],
        "heads": [
            2,
            4,
            8,
            16
        ]
    }
}